<graph>
<nodes>
<node id='215283089' x='11547.4' y='18647.2' />
<node id='215288154' x='11749.6' y='18753.4' />
<node id='218016626' x='12187.2' y='18242.6' />
<node id='218030458' x='11993.5' y='18480.3' />
<node id='223317863' x='11987.8' y='18120.5' />
<node id='234457229' x='12010.2' y='18498.4' />
<node id='238614968' x='12534.9' y='17880' />
<node id='238614990' x='12348.9' y='17941.9' />
<node id='238614995' x='12378.6' y='17968' />
<node id='238614998' x='12400.4' y='17993' />
<node id='246271867' x='12605.9' y='17822.3' />
<node id='246271916' x='12581.4' y='17792.6' />
<node id='246279218' x='12318.6' y='18079.1' />
<node id='246279219' x='12269.1' y='18048.7' />
<node id='246279220' x='12235.5' y='18030.7' />
<node id='246279221' x='12196.1' y='18007.4' />
<node id='246279222' x='12159.5' y='17985.8' />
<node id='246279225' x='12072.6' y='17985' />
<node id='246279227' x='12243' y='18093.7' />
<node id='246279228' x='12167.3' y='18060.6' />
<node id='246279229' x='12128.5' y='18039.1' />
<node id='246279230' x='12187.1' y='18113.4' />
<node id='246279232' x='12153.6' y='18120.7' />
<node id='246279234' x='12109.3' y='18192.3' />
<node id='246279235' x='12145.9' y='18132.8' />
<node id='246280212' x='11999.2' y='18373' />
<node id='246280213' x='12129.4' y='18205.2' />
<node id='2577262106' x='12451.6' y='17825.4' />
</nodes>
<edges>
<edge from='215283089' to='215288154' />
<edge from='215288154' to='215283089' />
<edge from='215288154' to='218030458' />
<edge from='218016626' to='218030458' />
<edge from='218016626' to='246279218' />
<edge from='218016626' to='246280213' />
<edge from='218030458' to='215288154' />
<edge from='218030458' to='218016626' />
<edge from='218030458' to='234457229' />
<edge from='223317863' to='246279234' />
<edge from='234457229' to='218030458' />
<edge from='238614968' to='238614998' />
<edge from='238614968' to='246271867' />
<edge from='238614968' to='2577262106' />
<edge from='238614990' to='238614995' />
<edge from='238614995' to='238614990' />
<edge from='238614995' to='238614998' />
<edge from='238614995' to='2577262106' />
<edge from='238614998' to='238614968' />
<edge from='238614998' to='238614995' />
<edge from='238614998' to='246279218' />
<edge from='246271867' to='238614968' />
<edge from='246271867' to='246271916' />
<edge from='246271916' to='246271867' />
<edge from='246279218' to='218016626' />
<edge from='246279218' to='238614998' />
<edge from='246279218' to='246279219' />
<edge from='246279219' to='246279218' />
<edge from='246279219' to='246279220' />
<edge from='246279219' to='246279227' />
<edge from='246279220' to='246279219' />
<edge from='246279220' to='246279221' />
<edge from='246279220' to='246279230' />
<edge from='246279221' to='246279220' />
<edge from='246279221' to='246279222' />
<edge from='246279221' to='246279228' />
<edge from='246279222' to='246279221' />
<edge from='246279222' to='246279225' />
<edge from='246279222' to='246279229' />
<edge from='246279225' to='246279222' />
<edge from='246279227' to='246279219' />
<edge from='246279228' to='246279221' />
<edge from='246279229' to='246279222' />
<edge from='246279230' to='246279220' />
<edge from='246279230' to='246279232' />
<edge from='246279232' to='246279230' />
<edge from='246279234' to='223317863' />
<edge from='246279234' to='246279235' />
<edge from='246279234' to='246280213' />
<edge from='246279235' to='246279234' />
<edge from='246280212' to='246280213' />
<edge from='246280213' to='218016626' />
<edge from='246280213' to='246279234' />
<edge from='246280213' to='246280212' />
<edge from='2577262106' to='238614968' />
<edge from='2577262106' to='238614995' />
</edges>
</graph>