<graph>
<nodes>
<node id='1597902151' x='18711.6' y='18577.7' type='node' />
<node id='2546740435' x='18507.5' y='18419.9' type='node' />
<node id='2546740500' x='18698.3' y='18638.9' type='node' />
<node id='258194452' x='18276.3' y='18197.4' type='node' />
<node id='258194804' x='18562' y='17968.2' type='node' />
<node id='258199140' x='18592.8' y='18101.6' type='node' />
<node id='259632160' x='18782.2' y='18734.6' type='node' />
<node id='259632564' x='18838.2' y='18800.3' type='node' />
<node id='288463355' x='18834' y='18686.4' type='node' />
<node id='317611281' x='18718.9' y='18712.2' type='node' />
<node id='317655245' x='18225.4' y='18755.3' type='node' />
<node id='3652408730' x='18569.2' y='17955.9' type='node' />
<node id='3652408733' x='18572.3' y='17972.5' type='node' />
<node id='72992820' x='18181.6' y='18124.4' type='base' />
<node id='83200583' x='18664.3' y='18963.3' type='node' />
<node id='83200585' x='18763.8' y='18853.1' type='node' />
<node id='83200586' x='18797.5' y='18801.3' type='node' />
<node id='83200587' x='18820.5' y='18779.2' type='node' />
<node id='83204473' x='18725.3' y='19033.7' type='node' />
<node id='83208244' x='18931.7' y='19044.3' type='node' />
<node id='cluster_2005214143_258197025' x='18544.7' y='18463.4' type='node' />
<node id='cluster_2546740483_29839168' x='18664.1' y='18599.5' type='node' />
</nodes>
<edges>
<edge from='1597902151' to='cluster_2546740483_29839168' />
<edge from='2546740435' to='258194452' />
<edge from='2546740435' to='cluster_2005214143_258197025' />
<edge from='2546740500' to='259632160' />
<edge from='2546740500' to='cluster_2546740483_29839168' />
<edge from='258194452' to='2546740435' />
<edge from='258194452' to='258194804' />
<edge from='258194452' to='72992820' />
<edge from='258194804' to='258194452' />
<edge from='258194804' to='3652408730' />
<edge from='258194804' to='3652408733' />
<edge from='258199140' to='cluster_2005214143_258197025' />
<edge from='259632160' to='2546740500' />
<edge from='259632160' to='288463355' />
<edge from='259632160' to='83200587' />
<edge from='259632564' to='83200587' />
<edge from='288463355' to='259632160' />
<edge from='317611281' to='83200586' />
<edge from='317655245' to='cluster_2005214143_258197025' />
<edge from='3652408730' to='258194804' />
<edge from='3652408733' to='258194804' />
<edge from='72992820' to='258194452' />
<edge from='83200583' to='83200585' />
<edge from='83200583' to='83204473' />
<edge from='83200585' to='83200583' />
<edge from='83200585' to='83200586' />
<edge from='83200585' to='83208244' />
<edge from='83200586' to='317611281' />
<edge from='83200586' to='83200585' />
<edge from='83200586' to='83200587' />
<edge from='83200587' to='259632160' />
<edge from='83200587' to='259632564' />
<edge from='83200587' to='83200586' />
<edge from='83204473' to='83200583' />
<edge from='83208244' to='83200585' />
<edge from='cluster_2005214143_258197025' to='2546740435' />
<edge from='cluster_2005214143_258197025' to='258199140' />
<edge from='cluster_2005214143_258197025' to='317655245' />
<edge from='cluster_2005214143_258197025' to='cluster_2546740483_29839168' />
<edge from='cluster_2546740483_29839168' to='1597902151' />
<edge from='cluster_2546740483_29839168' to='2546740500' />
<edge from='cluster_2546740483_29839168' to='cluster_2005214143_258197025' />
</edges>
</graph>