<graph>
<nodes>
<node id='1458506913' x='16629.8' y='10956.9' type='node' />
<node id='1458506921' x='15981.9' y='11007.2' type='node' />
<node id='1458506930' x='16340.8' y='11054.8' type='node' />
<node id='1458506947' x='16186.8' y='11103.4' type='node' />
<node id='1458506955' x='16324' y='11133.1' type='node' />
<node id='1458506971' x='16302' y='11231.3' type='node' />
<node id='1458506978' x='15699.9' y='11280' type='base' />
<node id='1458506981' x='15712.4' y='11285' type='node' />
<node id='204974659' x='16422.5' y='11064.1' type='node' />
<node id='204979265' x='16383.3' y='11058.6' type='node' />
<node id='204980322' x='16269.4' y='10822.9' type='node' />
<node id='204985382' x='16196.6' y='10978.1' type='node' />
<node id='258352387' x='15928.4' y='10909.3' type='node' />
<node id='295205048' x='15717.1' y='11246.4' type='node' />
<node id='295205052' x='15541.7' y='11128.7' type='node' />
<node id='634875048' x='16103.2' y='10980.6' type='node' />
<node id='cluster_1458506903_1614244154' x='16017.5' y='10936.9' type='node' />
<node id='cluster_1614244151_254003650' x='15940.2' y='10916.6' type='node' />
<node id='cluster_1614244174_204985052' x='16179.9' y='11025.9' type='node' />
<node id='cluster_204979396_204985385' x='16386.9' y='11025.4' type='node' />
</nodes>
<edges>
<edge from='1458506913' to='cluster_204979396_204985385' />
<edge from='1458506921' to='cluster_1458506903_1614244154' />
<edge from='1458506930' to='1458506955' />
<edge from='1458506930' to='204979265' />
<edge from='1458506930' to='cluster_1614244174_204985052' />
<edge from='1458506947' to='1458506955' />
<edge from='1458506955' to='1458506930' />
<edge from='1458506955' to='1458506947' />
<edge from='1458506955' to='1458506971' />
<edge from='1458506971' to='1458506955' />
<edge from='1458506978' to='1458506981' />
<edge from='1458506978' to='295205048' />
<edge from='1458506981' to='1458506978' />
<edge from='1458506981' to='295205048' />
<edge from='204974659' to='204979265' />
<edge from='204979265' to='1458506930' />
<edge from='204979265' to='204974659' />
<edge from='204979265' to='cluster_204979396_204985385' />
<edge from='204980322' to='204985382' />
<edge from='204985382' to='204980322' />
<edge from='204985382' to='cluster_1614244174_204985052' />
<edge from='204985382' to='cluster_204979396_204985385' />
<edge from='258352387' to='cluster_1614244151_254003650' />
<edge from='295205048' to='1458506978' />
<edge from='295205048' to='1458506981' />
<edge from='295205048' to='295205052' />
<edge from='295205048' to='cluster_1614244151_254003650' />
<edge from='295205052' to='295205048' />
<edge from='634875048' to='cluster_1458506903_1614244154' />
<edge from='634875048' to='cluster_1614244174_204985052' />
<edge from='cluster_1458506903_1614244154' to='1458506921' />
<edge from='cluster_1458506903_1614244154' to='634875048' />
<edge from='cluster_1458506903_1614244154' to='cluster_1614244151_254003650' />
<edge from='cluster_1614244151_254003650' to='258352387' />
<edge from='cluster_1614244151_254003650' to='295205048' />
<edge from='cluster_1614244151_254003650' to='cluster_1458506903_1614244154' />
<edge from='cluster_1614244174_204985052' to='1458506930' />
<edge from='cluster_1614244174_204985052' to='204985382' />
<edge from='cluster_1614244174_204985052' to='634875048' />
<edge from='cluster_204979396_204985385' to='1458506913' />
<edge from='cluster_204979396_204985385' to='204979265' />
<edge from='cluster_204979396_204985385' to='204985382' />
</edges>
</graph>