<graph>
<nodes>
<node id='1457826751' x='20271.4' y='12988.3' />
<node id='1457826766' x='20274.8' y='13010.7' />
<node id='1457826815' x='19829.7' y='13071.5' />
<node id='1457826837' x='20219.9' y='13079' />
<node id='1457826842' x='20377.7' y='13082.1' />
<node id='1457826974' x='19870.1' y='13164.7' />
<node id='1457826988' x='20304.6' y='13155.4' />
<node id='1457827002' x='19794.7' y='13171.2' />
<node id='1457827029' x='20225.6' y='13172.5' />
<node id='1457827158' x='20169.9' y='13197.7' />
<node id='1457827231' x='19803.4' y='13231.7' />
<node id='1457827250' x='19754.1' y='13239.3' />
<node id='1457827255' x='19741.7' y='13251.2' />
<node id='1457827293' x='19902.8' y='13276.6' />
<node id='1457827393' x='20326.6' y='13320.9' />
<node id='1457827419' x='20190.6' y='13346' />
<node id='1457856454' x='20267' y='12895' />
<node id='1457856460' x='19719.8' y='12921.3' />
<node id='1457856471' x='20600.7' y='12907.8' />
<node id='1457856494' x='19740.8' y='12973.9' />
<node id='1457856512' x='19736.7' y='13150.1' />
<node id='408479786' x='19812.5' y='12999.7' />
<node id='473174801' x='20049.7' y='13077.7' />
<node id='60271288' x='19832.2' y='12960.8' />
<node id='60274983' x='20269.7' y='12969.3' />
<node id='749988995' x='19850.8' y='12924.1' />
<node id='749989018' x='19877.6' y='12962.2' />
<node id='749989057' x='19788.6' y='12964.5' />
</nodes>
<edges>
<edge from='1457826751' to='1457826766' />
<edge from='1457826751' to='1457826842' />
<edge from='1457826751' to='60274983' />
<edge from='1457826766' to='1457826751' />
<edge from='1457826766' to='1457826837' />
<edge from='1457826766' to='1457826988' />
<edge from='1457826815' to='1457826974' />
<edge from='1457826837' to='1457826766' />
<edge from='1457826837' to='1457827029' />
<edge from='1457826837' to='473174801' />
<edge from='1457826842' to='1457826751' />
<edge from='1457826974' to='1457826815' />
<edge from='1457826974' to='1457827002' />
<edge from='1457826974' to='1457827158' />
<edge from='1457826988' to='1457826766' />
<edge from='1457827002' to='1457826974' />
<edge from='1457827002' to='1457827231' />
<edge from='1457827002' to='1457856512' />
<edge from='1457827029' to='1457826837' />
<edge from='1457827029' to='1457827158' />
<edge from='1457827029' to='1457827393' />
<edge from='1457827158' to='1457826974' />
<edge from='1457827158' to='1457827029' />
<edge from='1457827158' to='1457827419' />
<edge from='1457827231' to='1457827002' />
<edge from='1457827231' to='1457827250' />
<edge from='1457827231' to='1457827293' />
<edge from='1457827250' to='1457827231' />
<edge from='1457827250' to='1457827255' />
<edge from='1457827255' to='1457827250' />
<edge from='1457827293' to='1457827231' />
<edge from='1457827393' to='1457827029' />
<edge from='1457827419' to='1457827158' />
<edge from='1457856454' to='60274983' />
<edge from='1457856460' to='1457856494' />
<edge from='1457856471' to='60274983' />
<edge from='1457856494' to='1457856460' />
<edge from='1457856494' to='749989057' />
<edge from='1457856512' to='1457827002' />
<edge from='408479786' to='60271288' />
<edge from='473174801' to='1457826837' />
<edge from='60271288' to='408479786' />
<edge from='60271288' to='749988995' />
<edge from='60271288' to='749989018' />
<edge from='60271288' to='749989057' />
<edge from='60274983' to='1457826751' />
<edge from='60274983' to='1457856454' />
<edge from='60274983' to='1457856471' />
<edge from='60274983' to='749989018' />
<edge from='749988995' to='60271288' />
<edge from='749988995' to='749989018' />
<edge from='749989018' to='60271288' />
<edge from='749989018' to='60274983' />
<edge from='749989018' to='749988995' />
<edge from='749989057' to='1457856494' />
<edge from='749989057' to='60271288' />
</edges>
</graph>