<graph>
<nodes>
<node id='1146944330' x='13583.9' y='15254.7' />
<node id='1679579323' x='13610.4' y='15269.2' />
<node id='2084882004' x='14325.3' y='15695.9' />
<node id='2112725030' x='14211.8' y='15612.9' />
<node id='2366317807' x='14169.3' y='15698.6' />
<node id='248533576' x='14154.8' y='15707.7' />
<node id='256306787' x='14051.4' y='15844.9' />
<node id='256308413' x='13869.8' y='15693.8' />
<node id='256308414' x='13998.1' y='15834.6' />
<node id='256309724' x='13879.8' y='15564.8' />
<node id='256499699' x='14304.1' y='15693.5' />
<node id='256691759' x='14010.8' y='15592.2' />
<node id='256691909' x='13870.7' y='15683.9' />
<node id='256693683' x='13732.5' y='15415' />
<node id='256693685' x='13824.5' y='15517.2' />
<node id='256694645' x='13854.5' y='15883.9' />
<node id='2645429548' x='13852.9' y='15860.7' />
<node id='264845309' x='13815.2' y='15372.1' />
<node id='283884685' x='13909.3' y='15520.2' />
<node id='283884732' x='13896.9' y='15505.8' />
<node id='3022958022' x='14009.2' y='15919.5' />
<node id='310742819' x='14304.3' y='15664.4' />
<node id='311100324' x='13852.8' y='15861.2' />
<node id='311127914' x='14003.7' y='15518.1' />
<node id='311565736' x='13879.2' y='15704.1' />
<node id='311565998' x='13882.9' y='15686.8' />
<node id='311566116' x='13872.8' y='15666.3' />
<node id='32524496' x='13856.2' y='15847.2' />
<node id='32524506' x='14021.7' y='15711.5' />
<node id='cluster_1678199312_1678199317_2562090904_2866958696' x='13990.2' y='15971.2' />
<node id='cluster_2118856942_76474180' x='13713.5' y='15321.9' />
<node id='cluster_256309721_283845048' x='13817.1' y='15550.7' />
<node id='cluster_2664872747_2664872749_2664872750' x='14078.7' y='15835.4' />
<node id='cluster_32524342_32524343_32524497' x='14024.8' y='15842' />
</nodes>
<edges>
<edge from='1146944330' to='1679579323' />
<edge from='1679579323' to='1146944330' />
<edge from='1679579323' to='cluster_2118856942_76474180' />
<edge from='2084882004' to='256499699' />
<edge from='2112725030' to='2366317807' />
<edge from='2112725030' to='256691759' />
<edge from='2366317807' to='2112725030' />
<edge from='2366317807' to='248533576' />
<edge from='2366317807' to='256499699' />
<edge from='248533576' to='2366317807' />
<edge from='248533576' to='32524506' />
<edge from='248533576' to='cluster_2664872747_2664872749_2664872750' />
<edge from='256306787' to='cluster_2664872747_2664872749_2664872750' />
<edge from='256306787' to='cluster_32524342_32524343_32524497' />
<edge from='256308413' to='256691909' />
<edge from='256308413' to='311565736' />
<edge from='256308413' to='32524496' />
<edge from='256308414' to='cluster_32524342_32524343_32524497' />
<edge from='256309724' to='256691759' />
<edge from='256309724' to='283884685' />
<edge from='256309724' to='311566116' />
<edge from='256309724' to='cluster_256309721_283845048' />
<edge from='256499699' to='2084882004' />
<edge from='256499699' to='2366317807' />
<edge from='256499699' to='310742819' />
<edge from='256691759' to='2112725030' />
<edge from='256691759' to='256309724' />
<edge from='256691759' to='311127914' />
<edge from='256691759' to='32524506' />
<edge from='256691909' to='256308413' />
<edge from='256691909' to='311565998' />
<edge from='256691909' to='311566116' />
<edge from='256693683' to='256693685' />
<edge from='256693683' to='264845309' />
<edge from='256693685' to='256693683' />
<edge from='256693685' to='283884732' />
<edge from='256693685' to='cluster_256309721_283845048' />
<edge from='256694645' to='311100324' />
<edge from='2645429548' to='311100324' />
<edge from='2645429548' to='32524496' />
<edge from='2645429548' to='cluster_32524342_32524343_32524497' />
<edge from='264845309' to='256693683' />
<edge from='264845309' to='cluster_2118856942_76474180' />
<edge from='283884685' to='256309724' />
<edge from='283884685' to='283884732' />
<edge from='283884732' to='256693685' />
<edge from='283884732' to='283884685' />
<edge from='3022958022' to='cluster_32524342_32524343_32524497' />
<edge from='310742819' to='256499699' />
<edge from='311100324' to='256694645' />
<edge from='311100324' to='2645429548' />
<edge from='311127914' to='256691759' />
<edge from='311565736' to='256308413' />
<edge from='311565998' to='256691909' />
<edge from='311565998' to='32524506' />
<edge from='311566116' to='256309724' />
<edge from='311566116' to='256691909' />
<edge from='32524496' to='256308413' />
<edge from='32524496' to='2645429548' />
<edge from='32524506' to='248533576' />
<edge from='32524506' to='256691759' />
<edge from='32524506' to='311565998' />
<edge from='32524506' to='cluster_32524342_32524343_32524497' />
<edge from='cluster_1678199312_1678199317_2562090904_2866958696' to='cluster_32524342_32524343_32524497' />
<edge from='cluster_2118856942_76474180' to='1679579323' />
<edge from='cluster_2118856942_76474180' to='264845309' />
<edge from='cluster_256309721_283845048' to='256309724' />
<edge from='cluster_256309721_283845048' to='256693685' />
<edge from='cluster_2664872747_2664872749_2664872750' to='248533576' />
<edge from='cluster_2664872747_2664872749_2664872750' to='256306787' />
<edge from='cluster_2664872747_2664872749_2664872750' to='cluster_32524342_32524343_32524497' />
<edge from='cluster_32524342_32524343_32524497' to='256306787' />
<edge from='cluster_32524342_32524343_32524497' to='256308414' />
<edge from='cluster_32524342_32524343_32524497' to='2645429548' />
<edge from='cluster_32524342_32524343_32524497' to='3022958022' />
<edge from='cluster_32524342_32524343_32524497' to='32524506' />
<edge from='cluster_32524342_32524343_32524497' to='cluster_1678199312_1678199317_2562090904_2866958696' />
<edge from='cluster_32524342_32524343_32524497' to='cluster_2664872747_2664872749_2664872750' />
</edges>
</graph>