<graph>
<nodes>
<node id='1373730443' x='11328.4' y='16355.8' />
<node id='1373730465' x='11283' y='16507.5' />
<node id='151110200' x='11350.3' y='16283.7' />
<node id='151110209' x='11321' y='16244.8' />
<node id='151110230' x='11371' y='16217.1' />
<node id='1722236890' x='11254.2' y='16571.5' />
<node id='1722236923' x='11175.3' y='16712.6' />
<node id='1722236932' x='11144' y='16769.5' />
<node id='1722236945' x='11099.3' y='16846' />
<node id='1722236949' x='11078.7' y='16886.3' />
<node id='1722236968' x='11033.7' y='16957.5' />
<node id='1722236980' x='10962.6' y='17058.1' />
<node id='245798672' x='11069.1' y='17035.7' />
<node id='429505387' x='11235.2' y='16310.6' />
<node id='52155619' x='11304.9' y='16064.8' />
<node id='52155641' x='11208.1' y='16139.1' />
<node id='52155660' x='11189.1' y='16031' />
<node id='52155755' x='11392' y='16260.5' />
<node id='52155786' x='11435.8' y='16353.3' />
<node id='52155814' x='11321.6' y='16620.3' />
<node id='52689509' x='11194.3' y='16677.3' />
<node id='52689539' x='10951.6' y='17074' />
<node id='52689641' x='10964.4' y='16980.2' />
<node id='52689677' x='11102' y='16682.4' />
<node id='52689698' x='11155.9' y='16499.7' />
<node id='55175491' x='11238.2' y='16293.9' />
<node id='60220325' x='11251.5' y='16754.1' />
<node id='60220350' x='11251.1' y='16976.6' />
<node id='60220357' x='11165' y='16992.7' />
<node id='665671761' x='11306.5' y='16443.3' />
<node id='cluster_1373730451_52155742_665671742_665671743' x='11323.4' y='16383.7' />
<node id='cluster_1722236952_1722236962' x='11052.6' y='16929' />
<node id='cluster_1722236976_1722236978' x='11003.1' y='17002.2' />
<node id='cluster_52155630_52155637' x='11241' y='16110.7' />
</nodes>
<edges>
<edge from='1373730443' to='151110200' />
<edge from='1373730443' to='cluster_1373730451_52155742_665671742_665671743' />
<edge from='1373730465' to='1722236890' />
<edge from='1373730465' to='665671761' />
<edge from='1373730465' to='cluster_1373730451_52155742_665671742_665671743' />
<edge from='151110200' to='1373730443' />
<edge from='151110200' to='151110209' />
<edge from='151110200' to='52155755' />
<edge from='151110209' to='151110200' />
<edge from='151110209' to='151110230' />
<edge from='151110209' to='55175491' />
<edge from='151110209' to='cluster_52155630_52155637' />
<edge from='151110230' to='151110209' />
<edge from='1722236890' to='1373730465' />
<edge from='1722236890' to='52155814' />
<edge from='1722236890' to='52689509' />
<edge from='1722236890' to='52689698' />
<edge from='1722236923' to='1722236932' />
<edge from='1722236923' to='52689509' />
<edge from='1722236923' to='60220325' />
<edge from='1722236932' to='1722236923' />
<edge from='1722236932' to='1722236945' />
<edge from='1722236932' to='52689677' />
<edge from='1722236932' to='60220350' />
<edge from='1722236945' to='1722236932' />
<edge from='1722236945' to='1722236949' />
<edge from='1722236945' to='60220357' />
<edge from='1722236949' to='1722236945' />
<edge from='1722236949' to='cluster_1722236952_1722236962' />
<edge from='1722236968' to='cluster_1722236952_1722236962' />
<edge from='1722236968' to='cluster_1722236976_1722236978' />
<edge from='1722236980' to='52689539' />
<edge from='1722236980' to='cluster_1722236976_1722236978' />
<edge from='245798672' to='cluster_1722236976_1722236978' />
<edge from='429505387' to='cluster_1373730451_52155742_665671742_665671743' />
<edge from='52155619' to='cluster_52155630_52155637' />
<edge from='52155641' to='cluster_52155630_52155637' />
<edge from='52155660' to='cluster_52155630_52155637' />
<edge from='52155755' to='151110200' />
<edge from='52155786' to='cluster_1373730451_52155742_665671742_665671743' />
<edge from='52155814' to='1722236890' />
<edge from='52689509' to='1722236890' />
<edge from='52689509' to='1722236923' />
<edge from='52689509' to='52689677' />
<edge from='52689539' to='1722236980' />
<edge from='52689641' to='cluster_1722236976_1722236978' />
<edge from='52689677' to='1722236932' />
<edge from='52689677' to='52689509' />
<edge from='52689698' to='1722236890' />
<edge from='55175491' to='151110209' />
<edge from='60220325' to='1722236923' />
<edge from='60220350' to='1722236932' />
<edge from='60220357' to='1722236945' />
<edge from='60220357' to='cluster_1722236952_1722236962' />
<edge from='665671761' to='1373730465' />
<edge from='665671761' to='cluster_1373730451_52155742_665671742_665671743' />
<edge from='cluster_1373730451_52155742_665671742_665671743' to='1373730443' />
<edge from='cluster_1373730451_52155742_665671742_665671743' to='1373730465' />
<edge from='cluster_1373730451_52155742_665671742_665671743' to='429505387' />
<edge from='cluster_1373730451_52155742_665671742_665671743' to='52155786' />
<edge from='cluster_1373730451_52155742_665671742_665671743' to='665671761' />
<edge from='cluster_1722236952_1722236962' to='1722236949' />
<edge from='cluster_1722236952_1722236962' to='1722236968' />
<edge from='cluster_1722236952_1722236962' to='60220357' />
<edge from='cluster_1722236976_1722236978' to='1722236968' />
<edge from='cluster_1722236976_1722236978' to='1722236980' />
<edge from='cluster_1722236976_1722236978' to='245798672' />
<edge from='cluster_1722236976_1722236978' to='52689641' />
<edge from='cluster_52155630_52155637' to='151110209' />
<edge from='cluster_52155630_52155637' to='52155619' />
<edge from='cluster_52155630_52155637' to='52155641' />
<edge from='cluster_52155630_52155637' to='52155660' />
</edges>
</graph>