<graph>
<nodes>
<node id='1021041850' x='21187.4' y='13621.1' />
<node id='1590647545' x='21093.1' y='13946.7' />
<node id='1590647547' x='21052.5' y='13963.3' />
<node id='1590647550' x='21227.7' y='13965' />
<node id='1590647555' x='21371.4' y='14000.4' />
<node id='1590647565' x='21414.3' y='14104.7' />
<node id='1590647576' x='21182.5' y='14123.1' />
<node id='1590647582' x='21441.2' y='14169.7' />
<node id='1590777176' x='21348.4' y='13511.6' />
<node id='1590777246' x='21176.1' y='13642.4' />
<node id='1590777249' x='21061.3' y='13658.8' />
<node id='1596479378' x='21243.6' y='14205' />
<node id='278861069' x='21449.9' y='13969' />
<node id='278861082' x='21194' y='13636.8' />
<node id='278861101' x='21251.9' y='13829.8' />
<node id='278861102' x='21274.7' y='13884.4' />
<node id='278864451' x='21074.8' y='13902.1' />
<node id='278864453' x='21118.7' y='14008.9' />
<node id='278864455' x='21136' y='14051' />
<node id='278864697' x='21105.9' y='13769.1' />
<node id='278864701' x='21182.4' y='13858.2' />
<node id='278864702' x='21148.3' y='13872.1' />
<node id='278864703' x='21192.4' y='13979.2' />
<node id='278865278' x='21222.8' y='13953' />
<node id='278865279' x='21370.3' y='13845.5' />
<node id='278865282' x='21388.4' y='14043.9' />
<node id='278865289' x='21297.1' y='14081.7' />
<node id='278865291' x='21330.7' y='14163.8' />
<node id='3470243852' x='21254' y='14029.1' />
<node id='832548478' x='21351.5' y='14228.4' />
<node id='cluster_278861068_831295832' x='21484.3' y='13953.1' />
</nodes>
<edges>
<edge from='1021041850' to='278861082' />
<edge from='1590647545' to='1590647547' />
<edge from='1590647545' to='278864451' />
<edge from='1590647545' to='278864453' />
<edge from='1590647547' to='1590647545' />
<edge from='1590647550' to='278864703' />
<edge from='1590647550' to='278865278' />
<edge from='1590647550' to='3470243852' />
<edge from='1590647555' to='278861069' />
<edge from='1590647555' to='278861102' />
<edge from='1590647555' to='278865282' />
<edge from='1590647565' to='1590647582' />
<edge from='1590647565' to='278861069' />
<edge from='1590647565' to='278865282' />
<edge from='1590647576' to='278865289' />
<edge from='1590647582' to='1590647565' />
<edge from='1590777176' to='cluster_278861068_831295832' />
<edge from='1590777246' to='1590777249' />
<edge from='1590777246' to='278861082' />
<edge from='1590777246' to='278861101' />
<edge from='1590777249' to='1590777246' />
<edge from='1590777249' to='278864697' />
<edge from='1596479378' to='278865291' />
<edge from='278861069' to='1590647555' />
<edge from='278861069' to='1590647565' />
<edge from='278861069' to='cluster_278861068_831295832' />
<edge from='278861082' to='1021041850' />
<edge from='278861082' to='1590777246' />
<edge from='278861101' to='1590777246' />
<edge from='278861101' to='278861102' />
<edge from='278861101' to='278864701' />
<edge from='278861102' to='1590647555' />
<edge from='278861102' to='278861101' />
<edge from='278861102' to='278865279' />
<edge from='278864451' to='1590647545' />
<edge from='278864451' to='278864702' />
<edge from='278864453' to='1590647545' />
<edge from='278864453' to='278864455' />
<edge from='278864453' to='278864703' />
<edge from='278864455' to='278864453' />
<edge from='278864697' to='1590777249' />
<edge from='278864697' to='278864701' />
<edge from='278864701' to='278861101' />
<edge from='278864701' to='278864697' />
<edge from='278864701' to='278864702' />
<edge from='278864702' to='278864451' />
<edge from='278864702' to='278864701' />
<edge from='278864702' to='278864703' />
<edge from='278864703' to='1590647550' />
<edge from='278864703' to='278864453' />
<edge from='278864703' to='278864702' />
<edge from='278865278' to='1590647550' />
<edge from='278865279' to='278861102' />
<edge from='278865282' to='1590647555' />
<edge from='278865282' to='1590647565' />
<edge from='278865282' to='278865289' />
<edge from='278865289' to='1590647576' />
<edge from='278865289' to='278865282' />
<edge from='278865289' to='278865291' />
<edge from='278865291' to='1596479378' />
<edge from='278865291' to='278865289' />
<edge from='278865291' to='832548478' />
<edge from='3470243852' to='1590647550' />
<edge from='832548478' to='278865291' />
<edge from='cluster_278861068_831295832' to='1590777176' />
<edge from='cluster_278861068_831295832' to='278861069' />
</edges>
</graph>